py_simpace-2.0.1.dist-info/licenses/LICENSE
pysimpace/__init__.py
pysimpace/analysis.py
pysimpace/cli.py
pysimpace/gui.py
pysimpace/io.py
pysimpace/ml.py
pysimpace/simulation/__init__.py
pysimpace/simulation/functional.py
pysimpace/simulation/models.py
pysimpace/simulation/noise.py
pysimpace/simulation/structural.py
pysimpace/simulation/transforms.py
py_simpace-2.0.1.dist-info/METADATA
py_simpace-2.0.1.dist-info/WHEEL
py_simpace-2.0.1.dist-info/top_level.txt
py_simpace-2.0.1.dist-info/RECORD
