Metadata-Version: 2.4
Name: py-simpace
Version: 2.0.1
Summary: Realistic MRI motion artifact simulation toolkit for structural MRI and fMRI, with deep learning integration.
Home-page: https://github.com/snehil03july/py-SimPace
Author: Snehil Kumar
Author-email: sk895@exeter.ac.uk
Project-URL: Bug Tracker, https://github.com/snehil03july/py-SimPace/issues
Project-URL: Documentation, https://github.com/snehil03july/py-SimPace#readme
Classifier: Development Status :: 4 - Beta
Classifier: Intended Audience :: Science/Research
Classifier: Intended Audience :: Healthcare Industry
Classifier: License :: OSI Approved :: MIT License
Classifier: Programming Language :: Python :: 3
Classifier: Topic :: Scientific/Engineering :: Image Processing
Classifier: Topic :: Scientific/Engineering :: Medical Science Apps.
Classifier: Topic :: Scientific/Engineering :: Artificial Intelligence
Requires-Python: >=3.7
License-File: LICENSE
Requires-Dist: numpy>=1.21
Requires-Dist: scipy>=1.7
Requires-Dist: matplotlib>=3.5
Requires-Dist: nibabel>=3.2
Requires-Dist: torch>=1.10
Requires-Dist: tqdm>=4.62
Requires-Dist: scikit-image>=0.19
Provides-Extra: dev
Requires-Dist: pytest>=6.2; extra == "dev"
Requires-Dist: torchio>=0.18; extra == "dev"
Dynamic: author
Dynamic: author-email
Dynamic: classifier
Dynamic: description
Dynamic: description-content-type
Dynamic: home-page
Dynamic: license-file
Dynamic: project-url
Dynamic: provides-extra
Dynamic: requires-dist
Dynamic: requires-python
Dynamic: summary
